{
  "name" : "Cycle Detection",
  "testType" : "SINGLE",
  "input" : {
    "type" : "STANDARD",
    "fileName" : "input.txt"
  },
  "output" : {
    "type" : "STANDARD",
    "fileName" : "output.txt"
  },
  "tests" : [ {
    "input" : "5 7\n0 3\n0 4\n4 2\n4 3\n4 0\n2 1\n1 0\n",
    "output" : "4\n1\n2\n5\n6\n",
    "index" : 0,
    "active" : true
  }, {
    "input" : "2 1\n1 0\n",
    "output" : "-1\n",
    "index" : 1,
    "active" : true
  }, {
    "input" : "4 6\n0 1\n1 2\n2 0\n0 1\n1 3\n3 0\n",
    "output" : "3\n0\n1\n2\n",
    "index" : 2,
    "active" : true
  } ],
  "location" : "src/main/java/contest",
  "vmArgs" : "-Xmx1024M",
  "mainClass" : "Main",
  "taskClass" : "contest.CycleDetection",
  "checkerClass" : "net.egork.chelper.checkers.TokenChecker",
  "checkerParameters" : "",
  "testClasses" : [ ],
  "date" : "2020.11.27",
  "contestName" : "Library Checker",
  "truncate" : true,
  "inputClass" : "template.io.FastInput",
  "outputClass" : "template.io.FastOutput",
  "includeLocale" : false,
  "failOnOverflow" : false,
  "interactive" : false,
  "interactor" : "net.egork.chelper.tester.Interactor",
  "newThread" : true
}