{
  "name" : "P2740 [USACO4.2]草地排水Drainage Ditches",
  "testType" : "SINGLE",
  "input" : {
    "type" : "STANDARD",
    "fileName" : "input.txt"
  },
  "output" : {
    "type" : "STANDARD",
    "fileName" : "output.txt"
  },
  "tests" : [ {
    "input" : "5 4\n1 2 40\n1 4 20\n2 4 20\n2 3 30\n3 4 10\n",
    "output" : "50\n",
    "index" : 0,
    "active" : true
  } ],
  "location" : "src/main/java/contest",
  "vmArgs" : "-Xmx125M",
  "mainClass" : "Main",
  "taskClass" : "contest.P2740USACO42DrainageDitches",
  "checkerClass" : "net.egork.chelper.checkers.TokenChecker",
  "checkerParameters" : "",
  "testClasses" : [ ],
  "date" : "2021.01.23",
  "contestName" : "Luogu",
  "truncate" : true,
  "inputClass" : "template.io.FastInput",
  "outputClass" : "template.io.FastOutput",
  "includeLocale" : false,
  "failOnOverflow" : false,
  "interactive" : false,
  "interactor" : "net.egork.chelper.tester.Interactor",
  "newThread" : true
}