{
  "name" : "G. New Road Network",
  "testType" : "MULTI_NUMBER",
  "input" : {
    "type" : "STANDARD",
    "fileName" : "input.txt"
  },
  "output" : {
    "type" : "STANDARD",
    "fileName" : "output.txt"
  },
  "tests" : [ {
    "input" : "2\n4 3\n0011\n1110\n0111\n3 3\n011\n101\n110\n",
    "output" : "YES\n1 3\n2 3\n3 4\nNO\n",
    "index" : 0,
    "active" : true
  } ],
  "location" : "src/main/java/contest",
  "vmArgs" : "-Xmx256M",
  "mainClass" : "Main",
  "taskClass" : "contest.GNewRoadNetwork",
  "checkerClass" : "net.egork.chelper.checkers.TokenChecker",
  "checkerParameters" : "",
  "testClasses" : [ ],
  "date" : "2020.01.10",
  "contestName" : "Mail.Ru Cup 2018 Round 1",
  "truncate" : true,
  "inputClass" : "template.io.FastInput",
  "outputClass" : "template.io.FastOutput",
  "includeLocale" : false,
  "failOnOverflow" : false,
  "interactive" : false,
  "interactor" : "net.egork.chelper.tester.Interactor",
  "newThread" : true
}