{
  "name" : "Random Walk Queries",
  "testType" : "SINGLE",
  "input" : {
    "type" : "STANDARD",
    "fileName" : "input.txt"
  },
  "output" : {
    "type" : "STANDARD",
    "fileName" : "output.txt"
  },
  "tests" : [ ],
  "location" : "src/main/java/contest",
  "vmArgs" : "-Xmx256M",
  "mainClass" : "Main",
  "taskClass" : "contest.RandomWalkQueries",
  "checkerClass" : "net.egork.chelper.checkers.TokenChecker",
  "checkerParameters" : "",
  "testClasses" : [ "contest.RandomWalkQueriesTestCase" ],
  "date" : "2021.03.07",
  "contestName" : "CodeChef - March Challenge 2021 Division 1",
  "truncate" : true,
  "inputClass" : "template.io.FastInput",
  "outputClass" : "template.io.FastOutput",
  "includeLocale" : false,
  "failOnOverflow" : false,
  "interactive" : false,
  "interactor" : "net.egork.chelper.tester.Interactor",
  "newThread" : true
}