{
  "name" : "TaskD",
  "testType" : "SINGLE",
  "input" : {
    "type" : "STANDARD",
    "fileName" : "input.txt"
  },
  "output" : {
    "type" : "STANDARD",
    "fileName" : "output.txt"
  },
  "tests" : [ {
    "input" : "2 2\n3\n1 1 0\n1 2 10\n2 1 20",
    "output" : "Yes\n",
    "index" : 0,
    "active" : true
  }, {
    "input" : "2 3\n5\n1 1 0\n1 2 10\n1 3 20\n2 1 30\n2 3 40",
    "output" : "No\n",
    "index" : 1,
    "active" : true
  }, {
    "input" : "2 2\n3\n1 1 20\n1 2 10\n2 1 0",
    "output" : "No\n",
    "index" : 2,
    "active" : true
  }, {
    "input" : "3 3\n4\n1 1 0\n1 3 10\n3 1 10\n3 3 20",
    "output" : "Yes\n",
    "index" : 3,
    "active" : true
  }, {
    "input" : "2 2\n4\n1 1 0\n1 2 10\n2 1 30\n2 2 20",
    "output" : "No\n",
    "index" : 4,
    "active" : true
  }, {
    "input" : "2 2\n4\n1 1 100\n1 2 0\n2 1 100\n2 2 0",
    "output" : "Yes",
    "index" : 5,
    "active" : true
  }, {
    "input" : "2 2\n4\n1 1 100\n1 2 0\n2 1 100\n2 2 1",
    "output" : "No",
    "index" : 6,
    "active" : true
  }, {
    "input" : "2 3\n4\n1 1 1\n1 2 2 \n1 3 3\n2 2 0",
    "output" : "No",
    "index" : 7,
    "active" : true
  }, {
    "input" : "100000\n100000\n0",
    "output" : "Yes",
    "index" : 8,
    "active" : true
  }, {
    "input" : "3 3\n5\n1 1 1\n1 3 10\n2 2 0\n2 3 10\n3 1 0",
    "output" : "No",
    "index" : 9,
    "active" : true
  }, {
    "input" : "3 3\n5\n1 1 0\n2 2 10\n2 3 0\n3 1 10\n3 2 10",
    "output" : "No",
    "index" : 10,
    "active" : true
  } ],
  "location" : "src/main/java/contest",
  "vmArgs" : "-Xmx256m -Xss64m",
  "mainClass" : "Main",
  "taskClass" : "contest.TaskD",
  "checkerClass" : "net.egork.chelper.checkers.TokenChecker",
  "checkerParameters" : "",
  "testClasses" : [ ],
  "date" : "2019.10.12",
  "contestName" : "Atcoder codefestival 2016",
  "truncate" : true,
  "inputClass" : "template.FastInput",
  "outputClass" : "java.io.PrintWriter",
  "includeLocale" : false,
  "failOnOverflow" : false,
  "interactive" : false,
  "interactor" : "net.egork.chelper.tester.Interactor",
  "newThread" : true
}