{
  "name" : "E - Weights on Vertices and Edges",
  "testType" : "SINGLE",
  "input" : {
    "type" : "STANDARD",
    "fileName" : "input.txt"
  },
  "output" : {
    "type" : "STANDARD",
    "fileName" : "output.txt"
  },
  "tests" : [ {
    "input" : "4 4\n2 3 5 7\n1 2 7\n1 3 9\n2 3 12\n3 4 18\n",
    "output" : "2\n",
    "index" : 0,
    "active" : true
  }, {
    "input" : "6 10\n4 4 1 1 1 7\n3 5 19\n2 5 20\n4 5 8\n1 6 16\n2 3 9\n3 6 16\n3 4 1\n2 6 20\n2 4 19\n1 2 9\n",
    "output" : "4\n",
    "index" : 1,
    "active" : true
  }, {
    "input" : "10 9\n81 16 73 7 2 61 86 38 90 28\n6 8 725\n3 10 12\n1 4 558\n4 9 615\n5 6 942\n8 9 918\n2 7 720\n4 7 292\n7 10 414\n",
    "output" : "8\n",
    "index" : 2,
    "active" : true
  } ],
  "location" : "src/main/java/contest",
  "vmArgs" : "-Xmx1024M",
  "mainClass" : "Main",
  "taskClass" : "contest.EWeightsOnVerticesAndEdges",
  "checkerClass" : "net.egork.chelper.checkers.TokenChecker",
  "checkerParameters" : "",
  "testClasses" : [ ],
  "date" : "2020.07.17",
  "contestName" : "AtCoder - NIKKEI Programming Contest 2019",
  "truncate" : true,
  "inputClass" : "template.io.FastInput",
  "outputClass" : "template.io.FastOutput",
  "includeLocale" : false,
  "failOnOverflow" : false,
  "interactive" : false,
  "interactor" : "net.egork.chelper.tester.Interactor",
  "newThread" : true
}