{
  "name" : "Binary Subsequence",
  "testType" : "MULTI_NUMBER",
  "input" : {
    "type" : "STANDARD",
    "fileName" : "input.txt"
  },
  "output" : {
    "type" : "STANDARD",
    "fileName" : "output.txt"
  },
  "tests" : [ {
    "input" : "6\n2\n01\n3\n110\n5\n10101\n5\n10011\n6\n111000\n19\n1101000010110111010\n",
    "output" : "0\n1\n2\n1\n3\n7\n",
    "index" : 0,
    "active" : true
  } ],
  "location" : "src/main/java/contest",
  "vmArgs" : "-Xmx256M",
  "mainClass" : "Main",
  "taskClass" : "contest.BinarySubsequence",
  "checkerClass" : "net.egork.chelper.checkers.TokenChecker",
  "checkerParameters" : "",
  "testClasses" : [ ],
  "date" : "2021.01.30",
  "contestName" : "CodeChef - January Lunchtime 2021 Division 2",
  "truncate" : true,
  "inputClass" : "template.io.FastInput",
  "outputClass" : "template.io.FastOutput",
  "includeLocale" : false,
  "failOnOverflow" : false,
  "interactive" : false,
  "interactor" : "net.egork.chelper.tester.Interactor",
  "newThread" : true
}