{
  "name" : "The Closest M Points",
  "testType" : "MULTI_EOF",
  "input" : {
    "type" : "STANDARD",
    "fileName" : "input.txt"
  },
  "output" : {
    "type" : "STANDARD",
    "fileName" : "output.txt"
  },
  "tests" : [ {
    "input" : "3 2\n1 1\n1 3\n3 4\n2\n2 3\n2\n2 3\n1\n3 2\n1 1\n1 3\n3 4\n2\n2 3\n2\n2 3\n1\n",
    "output" : "the closest 2 points are:\n1 3\n3 4\nthe closest 1 points are:\n1 3\nthe closest 2 points are:\n1 3\n3 4\nthe closest 1 points are:\n1 3\n",
    "index" : 0,
    "active" : true
  } ],
  "location" : "src/main/java/contest",
  "vmArgs" : "-Xmx98M",
  "mainClass" : "Main",
  "taskClass" : "contest.TheClosestMPoints",
  "checkerClass" : "net.egork.chelper.checkers.TokenChecker",
  "checkerParameters" : "",
  "testClasses" : [ "contest.TheClosestMPointsTestCase" ],
  "date" : "2020.02.19",
  "contestName" : "HDU Online Judge",
  "truncate" : true,
  "inputClass" : "template.io.FastInput",
  "outputClass" : "template.io.FastOutput",
  "includeLocale" : false,
  "failOnOverflow" : false,
  "interactive" : false,
  "interactor" : "net.egork.chelper.tester.Interactor",
  "newThread" : false
}