{
  "name" : "J - Tiling Terrace",
  "testType" : "SINGLE",
  "input" : {
    "type" : "STANDARD",
    "fileName" : "input.txt"
  },
  "output" : {
    "type" : "STANDARD",
    "fileName" : "output.txt"
  },
  "tests" : [ {
    "input" : "6 4 10 25 40\n..#...\n",
    "output" : "75\n",
    "index" : 0,
    "active" : true
  }, {
    "input" : "6 4 10 100 40\n..#...\n",
    "output" : "210\n",
    "index" : 1,
    "active" : true
  }, {
    "input" : "7 2 30 10 100\n..#...#\n",
    "output" : "160\n",
    "index" : 2,
    "active" : true
  } ],
  "location" : "src/main/java/contest",
  "vmArgs" : "-Xmx256M",
  "mainClass" : "Main",
  "taskClass" : "contest.TaskJ",
  "checkerClass" : "net.egork.chelper.checkers.TokenChecker",
  "checkerParameters" : "",
  "testClasses" : [ ],
  "date" : "2019.11.27",
  "contestName" : "2019-2020 ICPC, Asia Jakarta Regional Contest (Online Mirror, ICPC Rules, Teams Preferred)",
  "truncate" : true,
  "inputClass" : "template.io.FastInput",
  "outputClass" : "template.io.FastOutput",
  "includeLocale" : false,
  "failOnOverflow" : false,
  "interactive" : false,
  "interactor" : "net.egork.chelper.tester.Interactor",
  "newThread" : true
}